ocrd_publaynet/__init__.py
ocrd_publaynet/import_mscoco.py
ocrd_publaynet-0.1.0.dist-info/METADATA
ocrd_publaynet-0.1.0.dist-info/WHEEL
ocrd_publaynet-0.1.0.dist-info/entry_points.txt
ocrd_publaynet-0.1.0.dist-info/top_level.txt
ocrd_publaynet-0.1.0.dist-info/RECORD
