Metadata-Version: 2.1
Name: ocrd-publaynet
Version: 0.1.0
Summary: convert PubLayNet data into METS/PAGE-XML
Home-page: https://github.com/bertsky/ocrd_publaynet
Author: Robert Sachunsky
Author-email: sachunsky@informatik.uni-leipzig.de
License: Apache License 2.0
Platform: UNKNOWN
Requires-Dist: ocrd (>=2.4.0)
Requires-Dist: click (>=7.0)
Requires-Dist: numpy
